{"./":{"url":"./","title":"概况","keywords":"","body":"Treeviewyax all right reserved, powered by aleen42 概述 概述 ... "},"docs/需求梳理.html":{"url":"docs/需求梳理.html","title":"需求梳理","keywords":"","body":"Treeviewyax all right reserved, powered by aleen42 需求梳理 (开发负责人)敖四平，周键杨 (开发负责人)：陈涛 (开发负责人)：江厚宏 (开发负责人)：陈龙，占欣伟 其他 需求澄清确认 需求梳理 (开发负责人)敖四平，周键杨 1. 人员编辑页面字段排序是否需优化，组织的命名——业务组织(实组织)，资源组织(虚组织)   2. 技能维度需求澄清——维度加上名称和打分   3. 新增客户字段位置调整   4. 新增客户阶段，海颐苑字段和银幸字段不统一，老人信息以及指定接待人 ——按照现有海逸苑原型   5. 入院流程资料必填项再确认——陈龙   6. 入院办理 甲方信息理应自动带入——自动带入，配置时必填   7. 合同和协议是否可以废弃？——合同可以废弃，协议不做废弃   8. 签约完成时，加上预期入住时间？——在入院流程中加上一列   9. 合同管理-合同可以废弃，不走流程，重新签订合同，额外服务按照新合同执行，新增协议干掉额外服务。   10. 入院办理-床位及收费信息，额外服务价格展示干掉，费用合计不是“元/天”   11. 入院之后，变更合同不允许修改床位及收费信息，如需变更需设计流程   12. 入院办理页面欠缺字段：合同开始结束日期，预缴费总金额，预缴周期（天）   13. 业务配置需要提供组织和管理岗之间的关系   14. 入住携带物品提示——支持点击下载附件，业务配置需支持配置附件   15. 重要事项知情告知，缺少不能入院的病况设置； 传染病 精神病 功能衰竭 皮肤病 自杀暴力史 室内吸烟，如果有以上问题做着重提醒   16. 特殊治疗和知情约定— —入院办理时增加扫描件上传，需明确附件内容  17. 入院增加生活自理能力，病人日常生活习惯  18. 护士/护工异动表：人员管理更改组织时记录调用日志。  19. 密码修改（按照原型入口位置来调整）、密码重置需补充完成  20. 参观评估之前是否校验长者基本信息是否需完善？——至少要完善姓名，性别，年龄  21. 实现上，目前无参观评估  22. 客户台账管理:长者到访登记为啥不叫“入院登记”？——确定更改为“发起入院”  23. 财务实现入院部分  24. 入院流程管理，入住登记按钮去掉 (开发负责人)：陈涛 1. 个案信息的个案类型干掉   2. 个案照会发布会议通知后，以消息通知形式通知各专业线人   3. 个案措施修改后需要保存小历史版本，照会制定的新计划，保存大历史版本 (开发负责人)：江厚宏 1. 入住管理状态控制需梳理，如果做串行是否存在问题？——入院签约完成生成待办(发给接待员)，点击待办进入入住接待页面，入住接待变成已完成，同时入住状态变为已入住，入住登记按钮干掉，后面流程不做任何限制   2. 七天适应期评估限制规则，页面布局调整，页面字段信息澄清（评估人字段有歧义）   3. 任务反馈需和统计数据打通   4. 档案管理中，合同只允许查看   5. 评估管理，评估表只新增不编辑   6. 入住适应性评估表固定7天，发布之前做二次提示，发布之后不允许修改，发布之前可任意修改   7. 档案管理菜单交互优化   8. 自带药品登记，签名如何协同？支持自带药品导出签名后扫描件上传  9. 过敏源丰富内容：区分药物过敏和食物过敏  10. 简易智能精神状态评估表，皮肤完整性评估检查登记表，支持在线录入评分结果，支持上传附件（主观书写的完整句子以及照样画图）  11. 入住适应性评估，入住护理评估一次入院只做单次评估，但要求能查询历史入院结果记录；服务评估复评，做历史版本但是不做版本对比，但是可以查看历史版本数据；其他评估量表均需实现历史版本及版本对比。  12. 入住管理，流程总状态意义何在？——去掉总状态，终止不做  13. 入住接待，是否应该去掉指定个案管理师？——干掉  14. 药品库警戒线提醒干掉  15. 计划及任务需要支持自定义配置（系统级(巡房)，临时的(约束/给氧)，日常/个案）  16. 计划类型需支持自定义添加 (开发负责人)：陈龙，占欣伟 1. 处置单，给氧类和约束类分类开发表单   2. 日常照护计划的修改，统一移到专业线操作入口，档案管理中照护计划管理直接干掉   3. 活动组织：只做记录，不做流程，活动记录内容参与人直接记录组织   4. 医嘱单管理：“存在冲突”-》“同意用药”   5. 修改个案措施，保存小历史版本   6. 每个专业线都要加上手工增加计划和任务，要限制计划名称(类型)  7. 日常照护计划的修改，统一移到专业线操作入口，档案管理中照护计划管理直接干掉  8. 财务管理 其他 1. 餐饮等级和床位调整需要设计流程   2. 夜巡时间记录表— —做成类似于措施的系统级任务 需求澄清确认 1. 组织结构目前不能完全支持自定义——ok   2. 服务列表 名称需再斟酌，为啥要加服务列表？商品管理是否ok？——家乐需要的，服务列表   3. 服务列表的商品来源，需确认？——参考原型   4. 班次管理是否需实现？——不实现   5. 项目同步是否需要实现？——不实现   6. 短期入住是否需要完成？如需做需重新梳理方案——暂时不搞   7. 入住适应性评估执行角色是？——评估人   8. 评估团队/个案团队，一个角色是否可以指定多个人——可以   9. 过敏源很重要   10. 财物管理，不做；   11. 档案管理-附件管理：干掉   12. 结案管理，离院管理，请假管理，不做   13. 外部的评估管理干掉   14. 排班、交班暂时不做   15. 物料管理不做，财务只做入院流程   16. 任务管理不做   17. 营养照护管理不做   18. 报表分析，流程配置不做   19. 物料管理不做，财务只做入院流程   20. 附件模板管理-不做 "},"docs/越秀养老项目数据库模型说明书.html":{"url":"docs/越秀养老项目数据库模型说明书.html","title":"越秀养老项目数据库模型说明书","keywords":"","body":"Treeviewyax all right reserved, powered by aleen42 越秀养老项目数据库模型说明书 第一章 引言 编写目的 特别说明 第二章 组织中心数据模型设计 1. 数据库 数据库名：db_organization 2. 数据表详情 业务组织表：business_organization 资源组织表：resource_organization 第三章 员工中心数据模型设计 1. 数据库 数据库名：db_organization 2. 数据表详情 员工表：staff 角色表：role 员工-数据权限绑定表：staff\\binding\\data_authority 员工-角色绑定表：staff\\binding\\role 第四章 统一认证中心数据模型设计 1. 数据库 数据库名：db_authentication 2. 数据表详情 人员表：person 账户表：account 第五章 客户中心数据模型设计 1. 数据库 库名：db_client 2. 数据表详情 客户信息表：client_info 第六章 养老客户中心数据模型设计 1. 数据库 库名：db\\beadhouse\\file 2. 数据表详情 长者信息表：elder_info 长者评估记录表：elder\\evaluate\\record 长者健康信息表：elder\\health\\record 第七章 商品中心数据模型设计 1. 数据库 库名：db_goods 2. 数据表详情 spu表：spu sku表：sku 床位表（bed) 房间表：room 反馈模版表：feedback 第八章 交易中心数据模型设计 1. 数据库 库名：db_transaction 2. 数据表详情 订单表：order 第九章 调度中心数据模型设计 1. 数据库 库名：db_schedule 2. 数据表详情 任务表：task 工作流表：workflow 第十章 配置中心数据模型设计 1. 数据库 库名：db_configuration 2. 数据表详情 字典表：dictionary 量表模版：assess\\table\\config 模块表：module 导因表：cause_configuration 诊断表：diagnosis_configuration 症状表：symptom 第十一章合约中心数据模型设计 1. 数据库 库名：db_contract 2. 数据表详情 合约表（contract_info） 越秀养老项目数据库模型说明书 (V1.0) 第一章 引言 编写目的 本文档是对越秀养老项目数据物理模型设计文档，明确数据库名、表名、字段名、数据类型、字段注释等数据信息，用来指导后期的开发, 本文档的读者对象是需求人员、系统设计人员、开发人员、测试人员。 特别说明 本模型设计采用非关系型数据库设计方法，不满足关系型数据库中的范式化设计，即一张表是一个集合（collection），每一条数据是一个文档（document）, 一个文档内有多个字段，每个字段可再内嵌文档。 {#section-1 .ListParagraph} 第二章 组织中心数据模型设计 1. 数据库 数据库名：db_organization 表清单： 表名 注释 business_organization 业务组织表 resource_organization 资源组织表 2. 数据表详情 业务组织表：business_organization 字段名 数据类型 注释 _id ObjectId 主键 pname String 父组织结构名称 pid String 父节点ID name String 组织名称 princapal String 负责人 tel String 联系电话 addr String 地址 email String 邮箱 fax String 传真 typeName String 类型名称 typeLevel String 类型级别 key String 类型key path String 路径 ids List 所属项目id childList List 子组织集 资源组织表：resource_organization 字段名 数据类型 注释 _id ObjectId 主键 pname String 父组织结构名称 pid String 父节点ID name String 组织名称 princapal String 负责人 tel String 联系电话 addr String 地址 email String 邮箱 fax String 传真 path String 路径 childList List 子组织集 第三章 员工中心数据模型设计 1. 数据库 数据库名：db_organization 表清单： 表名 注释 staff 员工表 role 角色表 staff_binding_data_authority 员工-数据权限绑定表 staff_binding_role 员工-角色绑定表 power 权限表 menu 菜单表 button 按钮表 2. 数据表详情 员工表：staff 字段名 数据类型 注释 _id ObjectId 主键 pId String 员工系统编号 name String 员工姓名 sex String 员工性别 account String 员工账号 accountStatus int 员工状态 number String 员工编号 birthday String 出生日期 identity String 身份证号码 marryStatus String 婚姻状态 onJob String 在职状态 education String 文化程度 nationality String 民族 roleName List 角色名列表 politicalStatus String 政治面貌 level String 等级 job String 职业 isAdmin boolean 是否为管理员账号 region String 所属区域 businessOrganizations BusinessOrganization 业务组织 resourceOrganizations ResourceOrganization 资源组织 角色表：role 字段名 数据类型 注释 _id ObjectId 主键 roleName String 角色名称 roleDesc String 角色描述 powerIds List 权限集 roleType String 角色类型 员工-数据权限绑定表：staff_binding_data_authority 字段名 数据类型 注释 _id ObjectId 主键 staffId String 员工Id businessId String 业务组织Id businessName String 组织名称 effectTime String 生效时间 loseEffectTime String 失效时间 员工-角色绑定表：staff_binding_role 字段名 数据类型 注释 _id ObjectId 主键 staffId String 员工Id roleId String 角色Id projectId String 项目Id 第四章 统一认证中心数据模型设计 1. 数据库 数据库名：db_authentication 数据表清单 表名 注释 person 人员表 account 账户表 staff_binding_data_authority 员工-数据权限绑定表 2. 数据表详情 人员表：person 字段名 数据类型 注释 _id ObjectId 主键，人员系统唯一Id name String 员工姓名 cellPhone String 手机号 identityCard String 证件号 certicicateType String 证件类型 账户表：account 字段名 数据类型 注释 _id ObjectId 主键 loginName String 账号名 accountStatue int 账号状态 passWord String 密码 salt String 盐 personId String 绑定的人员Id initTime String 生成时间 第五章 客户中心数据模型设计 1. 数据库 库名：db_client 数据表清单 表名 注释 client_info 客户信息表 2. 数据表详情 客户信息表：client_info 字段名 数据类型 注释 _id ObjectId 主键 clientId String 客户Id name String 姓名 gender String 性别 phone String 联系电话 wordUnit String 工作单位 nation String 民族 nativePlace String 籍贯 certificateType String 证件类型 idNumber String 证件号 birthday String 出生日期 houseboldAddr String 户籍地址 educationLevel String 文化程度 maritalStatus String 婚姻状态 language String 语言 religion String 宗教信仰 residenceStatus String 居住状态 hobby String 兴趣爱好 homeAddr String 家庭住址 personalDemand String 个性化需求 第六章 养老客户中心数据模型设计 1. 数据库 库名：db_beadhouse_file 数据表清单 表名 注释 elder_info 长者信息表 elder_evaluate_record 长者评估记录表 elder_health_record 长者健康信息表 2. 数据表详情 长者信息表：elder_info 字段名 数据类型 注释 _id ObjectId 主键 elderId String 长者Id name String 长者姓名 gender String 长者性别 phone String 长者联系电话 nation String 长者民族 nativePlace String 长者籍贯 certificateType String 证件类型 idNumber String 证件号 birthday String 出生日期 householdAddr String 户籍地址 educationLevel String 文化程度 maritalStatus String 婚姻状态 language String 语言 religion String 宗教信仰 residenceStatus String 居住状态 hobby String 兴趣爱好 homeAddr String 家庭住址 personalDemand String 个性化需求 elderAvatar OSSFile 长者头像 oss文件记录表：OSSFile 字段名 数据类型 注释 uid String name String 文件名 path String OSS内部文件路径 bucketName String OSS的bucket名字 downloadPath String 下载地址 长者评估记录表：elder_evaluate_record 字段名 数据类型 注释 _id ObjectId 主键 elderId String 长者Id name String 长者姓名 evaluaterList List 评估人列表 evaluateTime String 评估时间 evaluateType String 评估类型 evaluateTableVersion String 评估表版本 status String 评估状态 score Integter 评估总分 data Map 评估详情 evaluateOrigin String 评估来源 evaluateResult String 评估结果 EvaluaterPO 字段名 数据类型 注释 evaluaterId String 评估人Id evaluaterName String 评估人姓名 长者健康信息表：elder_health_record 字段名 数据类型 注释 _id ObjectId 主键 elderId String 长者Id healthInfoType String 健康信息类型 data String 评估信息 第七章 商品中心数据模型设计 1. 数据库 库名：db_goods 数据表清单 表名 注释 spu spu表 sku sku表 bed 床位表 room 房间表 feedback 反馈模版表 2. 数据表详情 spu表：spu 字段名 数据类型 注释 _id ObjectId 主键 projectId String 项目Id settingType String 所属类型 createTime Date 创建时间 modifyTime Date 修改时间 propertyValue List 属性信息 PropertyValue: 字段名 数据类型 注释 id String id name String 属性名 value String 属性值 sku表：sku 字段名 数据类型 注释 _id ObjectId 主键 operatorId String 操作人Id projectId String 项目Id settingType String 商品类型 serviceName String 服务名称 mnemonicCode String 助记码 price BigDecimal 服务价格 unit String 单位 takeEffectTime String 生效时间 loseEfficacyTime String 失效时间 remark String 备注 nurseContents List 措施内容 bedServices List 床位信息 cateringServices List 餐饮内容 goodsServices List 物品内容 床位表（bed) 字段名 数据类型 注释 _id ObjectId 主键 roomId String 房间Id bedName String 名称 condition List> 入住情况 state String 床位状态 remark String 备注 房间表：room 字段名 数据类型 注释 _id ObjectId 主键 projectId String 项目Id organizationId String 组织Id layerNumber String 楼层编号 roomNumber String 房间编号 number String 室号 region String 所属区域 反馈模版表：feedback 字段名 数据类型 注释 _id ObjectId 主键 projectId String 项目Id feedbackName String 反馈名称 userName String 修改人 userId String 修改人Id editTime String 修改时间 feedbackBills List 反馈项明细 FeedbackBill: 字段名 数据类型 注释 name String 反馈项名称 type String 反馈项类型 value Object 反馈项属性值 第八章 交易中心数据模型设计 1. 数据库 库名：db_transaction 数据表清单 表名 注释 order 订单表 2. 数据表详情 订单表：order 字段名 数据类型 注释 _id ObjectId 主键 projectId String 项目Id consigneeId String 收货人Id consigneeName String 收货人姓名 beginTime String 订单开始时间 endTime String 订单结束时间 payerId String 付款人id payerName String 付款人姓名 orderState String 订单状态 price String 价格 orderNum String 订单编号 type String 类型 origin String 来源 custom Map 定制数据 orderDetailList List 订单详情列表 OrderDetailPO: 字段名 数据类型 注释 uuid String 唯一标示 state String 状态 goodsId String 商品Id name String 商品名称 amount String 数量 consigneeId String 收货人Id consigneeName String 收货人姓名 custom Map 定制数据 第九章 调度中心数据模型设计 1. 数据库 库名：db_schedule 数据表清单 表名 注释 task 任务表 workflow 工作流表 2. 数据表详情 任务表：task 字段名 数据类型 注释 _id ObjectId 主键 taskName String 任务名称 taskContent String 任务内容 taskTarget TaskTargetPO 任务对象 taskExecutorList List 执行人列表 billDetailPlanId String 详情计划Id taskType String 任务类型 taskOrigin String 任务来源 sponsorId String 发起人Id sponsorName String 发起人姓名 sponsorTime String 发起时间 executorId String 实际执行人Id executorName String 实际执行人姓名 priorityLevel int 优先级 status String 状态 feedbackId String 反馈模版Id feedbackValue Mao 反馈内容 reminderTime String 任务提醒时间 startTime String 计划开始时间 endTIme String 计划结束时间 finishTime String 任务完成时间 cancelTime String 任务取消时间 projectId String 所属项目Id end boolean 是否已发送 workflow boolean 是否为工作流 lastModifiedTime String 最后修改时间 工作流表：workflow 字段名 数据类型 注释 _id ObjectId 主键 name String 工作流名称 key String 编码 operationRecordList List 操作记录列表 workflowTaskCaseGroupList List 工作流任务组 step int 当前步骤 status String 工作流状态 sponsorId String 发起人Id sponsorName String 发起人姓名 sponsorTime String 发起时间 startTime String 工作流开始时间 projectId String 项目Id 第十章 配置中心数据模型设计 1. 数据库 库名：db_configuration 数据表清单 表名 注释 dictionary 字典表 access_table_config 量表模版表 module 模块表 cause_configuration 导因表 diagnosis_configuration 诊断表 symptom_configuration 症状表 2. 数据表详情 字典表：dictionary 字段名 数据类型 注释 _id ObjectId 主键 key String key name String 名称 options List 选项列表 insertTime Date 插入时间 lastModTime Date 最后修改时间 DicOption: 字段名 数据类型 注释 key String key name String 名称 value int 值 insertTime Date 插入时间 lastModTime Date 最后修改时间 custom Object 自定义内容 量表模版：assess_table_config 字段名 数据类型 注释 _id ObjectId 主键 projectId String 项目Id assessTableId String 量表唯一标示Id assessTableName String 量表名称 totalScore int 总分值 modifyTime String 修改时间 version String 版本号 takeEffect Boolean 是否生效 assessItems List 量表项目集 assessResults List 量表评估结果集 AssessItemPO 字段名 数据类型 注释 id String id itemTitle String 项目名称 itemScore int 项目分数 assessTopics List 项目题目集 AssessResultPO: 字段名 数据类型 注释 minScore int 最小分值 maxScore int 最大分值 assessResult String 评估结果 模块表：module 字段名 数据类型 注释 _id ObjectId 主键 name String 名字 key String 名字对应的key roleIdList List 权限角色id列表 导因表：cause_configuration 字段名 数据类型 注释 _id ObjectId 主键 name String 导因名称 createTime Date 创建时间 modTime Date 修改时间 isCheak String 是否勾选 诊断表：diagnosis_configuration 字段名 数据类型 注释 _id ObjectId 主键 diagnosisName String 诊断名称 createTime Date 创建时间 modTime Date 修改时间 isCheak String 是否勾选 症状表：symptom 字段名 数据类型 注释 _id ObjectId 主键 name String 症状名称 createTime Date 创建时间 modTime Date 修改时间 isCheak String 是否勾选 第十一章合约中心数据模型设计 1. 数据库 库名：db_contract 数据表清单 表名 注释 contract_info 合约表 2. 数据表详情 合约表（contract_info） 字段名 数据类型 注释 _id ObjectId 主键 contractNo String 合同编号 firstParty String 甲方 firstAddress String 甲方地址 firstPhone String 甲方联系方式 secondParty String 乙方 secondSex String 乙方性别 secondEducation String 乙方文化程度 certificateType String 乙方证件类型 identifyNumber String 乙方身份证号码 homeAddress String 乙方家庭地址 scondContracts List 乙方监护人 agreements List 协议信息 attachmentPO AttachmentPO 附件 effectTime String 生效时间 loseEffectTime String 失效时间 hospitalizedTime String 入院时间 projectId String 项目Id submit boolean 保存状态 AgreementPO 字段名 数据类型 注释 _id String 协议Id protocolNo String 协议编号 protocolName String 协议名称 contractId String 合同Id elderId String 长者Id signTime String 签约时间 effectTime String 协议生效时间 loseEffectTime String 协议失效时间 uploadMany List 协议附件 "}}